LICENSE
MANIFEST.in
README.rst
setup.cfg
setup.py
versioneer.py
pygypsy/__init__.py
pygypsy/_version.py
pygypsy/asaCompileAgeGivenSpSiHt.py
pygypsy/basal_area_factor.py
pygypsy/basal_area_increment.c
pygypsy/basal_area_increment.pyx
pygypsy/basal_area_simulate.py
pygypsy/data_prep.py
pygypsy/density.py
pygypsy/exceptions.py
pygypsy/forward_simulation.py
pygypsy/io.py
pygypsy/log.py
pygypsy/path.py
pygypsy/plot.py
pygypsy/site_index.py
pygypsy/stand_density_factor.py
pygypsy/utils.py
pygypsy/volume.py
pygypsy.egg-info/PKG-INFO
pygypsy.egg-info/SOURCES.txt
pygypsy.egg-info/dependency_links.txt
pygypsy.egg-info/entry_points.txt
pygypsy.egg-info/not-zip-safe
pygypsy.egg-info/requires.txt
pygypsy.egg-info/top_level.txt
pygypsy/scripts/__init__.py
pygypsy/scripts/callbacks.py
pygypsy/scripts/cli.py
pygypsy/scripts/config/conf.schema
pygypsy/scripts/config/default-conf.json